condb/ConDB.py
condb/__init__.py
condb/client.py
condb/csv.py
condb/dbdig.py
condb/http_client.py
condb/py3.py
condb/signature.py
condb/timelib.py
condb/version.py
condb/ui/condb_ui.py
condb/ui/cli/__init__.py
condb/ui/cli/cli.py
condb-2.0.0.dist-info/LICENSE
condb-2.0.0.dist-info/METADATA
condb-2.0.0.dist-info/WHEEL
condb-2.0.0.dist-info/entry_points.txt
condb-2.0.0.dist-info/top_level.txt
condb-2.0.0.dist-info/RECORD
